README.md
setup.cfg
setup.py
src/dinjatags/__init__.py
src/dinjatags/library.py
src/dinjatags/loader.py
src/dinjatags.egg-info/PKG-INFO
src/dinjatags.egg-info/SOURCES.txt
src/dinjatags.egg-info/dependency_links.txt
src/dinjatags.egg-info/requires.txt
src/dinjatags.egg-info/top_level.txt