Metadata-Version: 1.1
Name: dinjatags
Version: 0.0.1a2
Summary: Library for loading Jinja2 Filters and Tags like django tags
Home-page: https://github.com/rjusher/dinjatags
Author: Raymond Joseph Usher Roche
Author-email: rjusher+pypi@gmail.com
License: BSD
Download-URL: https://github.com/rjusher/dinjatags/archive/v0.0.1-alpha1.tar.gz
Keywords: django,Jinja2
Platform: UNKNOWN
Classifier: Topic :: Database :: Front-Ends
Classifier: Programming Language :: Python
Classifier: Intended Audience :: Developers
Classifier: Environment :: Web Environment
Classifier: Framework :: Django
Classifier: Programming Language :: Python :: 3.6
Classifier: Topic :: Internet :: WWW/HTTP
Classifier: Topic :: Internet :: WWW/HTTP :: Dynamic Content
Classifier: Topic :: Internet :: WWW/HTTP :: WSGI
Classifier: Topic :: Software Development :: Libraries :: Application Frameworks
Classifier: Topic :: Software Development :: Libraries :: Python Modules
Classifier: License :: OSI Approved :: BSD License
